qabot/__init__.py
qabot/agent.py
qabot/cli.py
qabot/config.py
qabot/download_utils.py
qabot/formatting.py
qabot/llm.py
qabot/functions/__init__.py
qabot/functions/data_loader.py
qabot/functions/describe_duckdb_table.py
qabot/functions/duckdb_query.py
qabot/functions/wikidata.py
qabot/prompts/__init__.py
qabot/prompts/system.py
qabot-0.7.2.dist-info/LICENSE
qabot-0.7.2.dist-info/METADATA
qabot-0.7.2.dist-info/WHEEL
qabot-0.7.2.dist-info/entry_points.txt
qabot-0.7.2.dist-info/top_level.txt
qabot-0.7.2.dist-info/RECORD
