Metadata-Version: 2.2
Name: qabot
Version: 0.7.2
Summary: Query local or remote data files with natural language queries powered by OpenAI and DuckDB.
Author-email: Brian Thorne <brian@hardbyte.nz>
Requires-Python: >=3.11
License-File: LICENSE
Requires-Dist: openai<2.0,>=1.40
Requires-Dist: typer<0.13.0,>=0.12.5
Requires-Dist: rich<14.0,>=13.8
Requires-Dist: httpx<1.0,>0.27
Requires-Dist: tenacity<10.0,>=9.0
Requires-Dist: pydantic<3.0,>=2.5.3
Requires-Dist: pydantic-settings<3.0,>=2.2
Requires-Dist: appdirs<2.0,>=1.4.4
Requires-Dist: duckdb<2.0,>=1.2
